quinnat/__init__.py
quinnat/quinnat.py
quinnat-1.0.5.dist-info/LICENSE.txt
quinnat-1.0.5.dist-info/METADATA
quinnat-1.0.5.dist-info/WHEEL
quinnat-1.0.5.dist-info/top_level.txt
quinnat-1.0.5.dist-info/RECORD
