Metadata-Version: 2.1
Name: quinnat
Version: 1.0.5
Summary: Library for building chatbots on urbit
Home-page: https://github.com/midsum-salrux/quinnat
Author: ~midsum-salrux
Author-email: 
License: UNKNOWN
Platform: UNKNOWN
Requires-Python: >=3.0
License-File: LICENSE.txt
Requires-Dist: urlock
